gpx/__init__.py
gpx/__main__.py
gpx/base.py
gpx/bounds.py
gpx/cli.py
gpx/convert.py
gpx/copyright.py
gpx/email.py
gpx/gpx.py
gpx/io.py
gpx/link.py
gpx/metadata.py
gpx/person.py
gpx/py.typed
gpx/route.py
gpx/track.py
gpx/track_segment.py
gpx/types.py
gpx/utils.py
gpx/waypoint.py
gpx-2026.1.0.dist-info/WHEEL
gpx-2026.1.0.dist-info/entry_points.txt
gpx-2026.1.0.dist-info/METADATA
gpx-2026.1.0.dist-info/RECORD
