Metadata-Version: 2.3
Name: gpx
Version: 2026.1.0
Summary: gpx is a zero-dependency, pure Python package for reading, manipulating, writing and converting GPX files.
Keywords: gpx,gps,xml,geojson
Author: Steven van de Graaf
Author-email: Steven van de Graaf <steven@vandegraaf.xyz>
License: gpx
Classifier: Development Status :: 4 - Beta
Classifier: License :: OSI Approved :: GNU General Public License v3 or later (GPLv3+)
Classifier: Programming Language :: Python
Classifier: Programming Language :: Python :: 3
Classifier: Programming Language :: Python :: 3.11
Classifier: Programming Language :: Python :: 3.12
Classifier: Programming Language :: Python :: 3.13
Classifier: Programming Language :: Python :: 3.14
Classifier: Typing :: Typed
Requires-Python: >=3.11, <4
Project-URL: Changelog, https://gpx.readthedocs.io/en/stable/changelog.html
Project-URL: Documentation, https://gpx.readthedocs.io/en/stable/
Project-URL: Issue Tracker, https://github.com/sgraaf/gpx/issues
Project-URL: Source Code, https://github.com/sgraaf/gpx
